Metadata-Version: 2.4
Name: numcodecs_wasm_jpeg2000
Version: 0.3.0
Summary: numcodecs-jpeg2000 compression codec compiled to WebAssembly
Author-email: Juniper Tyree <juniper.tyree@helsinki.fi>
Maintainer-email: Juniper Tyree <juniper.tyree@helsinki.fi>
License: Copyright (c) 2024-2025, Juniper Tyree
Requires-Python: >=3.10
Requires-Dist: numcodecs-wasm~=0.2.0
